bulk_api_client/__init__.py
bulk_api_client/app.py
bulk_api_client/client.py
bulk_api_client/data-warehouse.pivot.pem
bulk_api_client/env_client.py
bulk_api_client/exceptions.py
bulk_api_client/model.py
bulk_api_client/models.py
bulk_api_client/query_helpers.py
bulk_api_client-3.4.1.dist-info/METADATA
bulk_api_client-3.4.1.dist-info/WHEEL
bulk_api_client-3.4.1.dist-info/top_level.txt
bulk_api_client-3.4.1.dist-info/RECORD
